llmv/__init__.py
llmv/__main__.py
llmv/chat.py
llmv/llm_template.py
llmv/llmv.py
llmv/prompt.py
llmv-0.1.8.dist-info/METADATA
llmv-0.1.8.dist-info/WHEEL
llmv-0.1.8.dist-info/entry_points.txt
llmv-0.1.8.dist-info/top_level.txt
llmv-0.1.8.dist-info/RECORD
